certleak/__init__.py
certleak/version.py
certleak/actions/__init__.py
certleak/actions/basicaction.py
certleak/actions/databaseaction.py
certleak/actions/logaction.py
certleak/actions/savefileaction.py
certleak/actions/savejsonaction.py
certleak/actions/telegramaction.py
certleak/actions/webhookaction.py
certleak/actions/tests/__init__.py
certleak/actions/tests/basicaction_test.py
certleak/actions/tests/savefileaction_test.py
certleak/actions/tests/savejsonaction_test.py
certleak/actions/tests/webhookaction_test.py
certleak/analyzers/README.md
certleak/analyzers/__init__.py
certleak/analyzers/alwaystrueanalyzer.py
certleak/analyzers/authoritykeyidanalyzer.py
certleak/analyzers/basicanalyzer.py
certleak/analyzers/cafingerprintanalyzer.py
certleak/analyzers/dnstwistanalyzer.py
certleak/analyzers/domainregexanalyzer.py
certleak/analyzers/fulldomainanalyzer.py
certleak/analyzers/letsencryptanalyzer.py
certleak/analyzers/precertanalyzer.py
certleak/analyzers/regexdomainanalyzer.py
certleak/analyzers/subdomainanalyzer.py
certleak/analyzers/tldanalyzer.py
certleak/analyzers/wildcardcertanalyzer.py
certleak/analyzers/x509analyzer.py
certleak/analyzers/tests/__init__.py
certleak/analyzers/tests/alwaystrueanalyzer_test.py
certleak/analyzers/tests/authoritykeyidanalyzer_test.py
certleak/analyzers/tests/basicanalyzer_test.py
certleak/analyzers/tests/domainregexanalyzer_test.py
certleak/analyzers/tests/fulldomainanalyzer_test.py
certleak/analyzers/tests/mergedanalyzer_test.py
certleak/analyzers/tests/precertanalyzer_test.py
certleak/analyzers/tests/subdomainanalyzer_test.py
certleak/analyzers/tests/wildcardcertanalyzer_test.py
certleak/analyzers/tests/x509analyzer_test.py
certleak/core/__init__.py
certleak/core/actionhandler.py
certleak/core/analyzerhandler.py
certleak/core/certleak.py
certleak/core/certstreamwrapper.py
certleak/core/certstreamdata/__init__.py
certleak/core/certstreamdata/certstreamobject.py
certleak/core/certstreamdata/chain.py
certleak-0.1.1.dist-info/licenses/LICENSE
certleak-0.1.1.dist-info/METADATA
certleak-0.1.1.dist-info/WHEEL
certleak-0.1.1.dist-info/top_level.txt
certleak-0.1.1.dist-info/RECORD
