Metadata-Version: 2.4
Name: certleak
Version: 0.1.1
Summary: Python tool to monitor and analyze TLS certificates as they are issued via certstream.
Author-email: d-Rickyy-b <certleak@rico-j.de>
License: MIT License
Project-URL: Homepage, https://github.com/d-Rickyy-b/certleak
Project-URL: Issues, https://github.com/d-Rickyy-b/certleak/issues
Keywords: python,certificate,tls,osint,framework
Classifier: Development Status :: 5 - Production/Stable
Classifier: Environment :: Console
Classifier: Intended Audience :: Developers
Classifier: Intended Audience :: Science/Research
Classifier: License :: OSI Approved :: MIT License
Classifier: Operating System :: OS Independent
Classifier: Topic :: Software Development :: Libraries :: Python Modules
Classifier: Topic :: Security
Classifier: Topic :: Internet
Classifier: Programming Language :: Python
Classifier: Programming Language :: Python :: 3
Classifier: Programming Language :: Python :: 3.9
Classifier: Programming Language :: Python :: 3.10
Classifier: Programming Language :: Python :: 3.11
Classifier: Programming Language :: Python :: 3.12
Requires-Python: >=3.9
License-File: LICENSE
Requires-Dist: certstream>=1.12
Requires-Dist: dnstwist>=20240812
Requires-Dist: requests>=2.32
Requires-Dist: tldextract>=5.0
Provides-Extra: dev
Requires-Dist: ruff; extra == "dev"
Dynamic: license-file
